LinguAlign/__init__.py
LinguAlign/aligners.py
LinguAlign/multiple_translations.py
LinguAlign/translation.py
LinguAlign/utils.py
lingualign-0.1.dist-info/LICENSE
lingualign-0.1.dist-info/WHEEL
lingualign-0.1.dist-info/METADATA
lingualign-0.1.dist-info/RECORD
