Metadata-Version: 2.1
Name: LinguAlign
Version: 0.1
Summary: An amazing sample package!dd
Author-email: lfc <lfc@di.uminho.pt>
Classifier: License :: OSI Approved :: MIT License
